mcp_markdown/__init__.py
mcp_markdown-0.3.1.dist-info/METADATA
mcp_markdown-0.3.1.dist-info/WHEEL
mcp_markdown-0.3.1.dist-info/entry_points.txt
mcp_markdown-0.3.1.dist-info/RECORD
