Metadata-Version: 2.4
Name: mcp-markdown
Version: 0.3.1
Summary: Add your description here
Author: 刘松奇
Requires-Python: >=3.11
Requires-Dist: mcp[cli]>=1.11.0
